moody/__init__.py
moody/moody.py
moody-0.2.3.dist-info/LICENSE
moody-0.2.3.dist-info/METADATA
moody-0.2.3.dist-info/WHEEL
moody-0.2.3.dist-info/entry_points.txt
moody-0.2.3.dist-info/top_level.txt
moody-0.2.3.dist-info/RECORD
