Metadata-Version: 2.1
Name: moody
Version: 0.2.3
Summary: A basic CLI to download data from the Mars ODE PDS Node
Home-page: https://github.com/andrewannex/moody
Download-URL: https://github.com/AndrewAnnex/moody/archive/0.2.3.tar.gz
Author: Andrew Annex
Author-email: annex@jhu.edu
License: MIT
Keywords: mars,nasa,ode,pds,cli,tool
Classifier: Natural Language :: English
Classifier: License :: OSI Approved :: MIT License
Classifier: Development Status :: 3 - Alpha
Classifier: Environment :: Console
Classifier: Intended Audience :: Developers
Classifier: Intended Audience :: Science/Research
Classifier: Programming Language :: Python :: 3 :: Only
Classifier: Programming Language :: Python :: 3.6
Classifier: Programming Language :: Python :: 3.7
Classifier: Programming Language :: Python :: 3.8
Classifier: Programming Language :: Python :: 3.9
Classifier: Programming Language :: Python :: 3.10
Classifier: Programming Language :: Python :: 3.11
Classifier: Topic :: Scientific/Engineering :: Astronomy
Classifier: Topic :: Scientific/Engineering :: GIS
License-File: LICENSE
Requires-Dist: requests
Requires-Dist: fire
Requires-Dist: tqdm
